setup.py
cfg/rpclient.ini
rpclient/__init__.py
rpclient.egg-info/PKG-INFO
rpclient.egg-info/SOURCES.txt
rpclient.egg-info/dependency_links.txt
rpclient.egg-info/not-zip-safe
rpclient.egg-info/requires.txt
rpclient.egg-info/top_level.txt