Metadata-Version: 1.0
Name: rpclient
Version: 0.8
Summary: The RabbitMQ Server's RPC Client
Home-page: http://infinite.mn/
Author: Infinite Solutions LLC
Author-email: ganzorig@infinite.mn
License: GNU
Keywords: rpc rpclient rpcclient rabbitmq pika
Platform: UNKNOWN
